smsaero_kannel/__init__.py
smsaero_kannel/async_kannel.py
smsaero_kannel/cmd_kannel_server.py
smsaero_kannel/cmd_send.py
smsaero_kannel/constants.py
smsaero_kannel/dlr_server.py
smsaero_kannel/errors.py
smsaero_kannel/kannel.py
smsaero_kannel/logging.py
smsaero_kannel/retry.py
smsaero_kannel/types.py
smsaero_kannel/validators.py
smsaero_kannel-1.0.3.dist-info/licenses/AUTHORS.md
smsaero_kannel-1.0.3.dist-info/licenses/LICENSE
smsaero_kannel-1.0.3.dist-info/METADATA
smsaero_kannel-1.0.3.dist-info/WHEEL
smsaero_kannel-1.0.3.dist-info/entry_points.txt
smsaero_kannel-1.0.3.dist-info/top_level.txt
smsaero_kannel-1.0.3.dist-info/RECORD
