Metadata-Version: 2.4
Name: smsaero_kannel
Version: 1.0.3
Summary: SMS Aero Kannel Lib
Home-page: https://github.com/smsaero/smsaero_python_kannel/
Download-URL: https://github.com/smsaero/smsaero_python_kannel/archive/refs/tags/1.0.1.tar.gz
Author: SmsAero
Author-email: admin@smsaero.ru
Maintainer: SmsAero Team
Maintainer-email: support@smsaero.ru
License: MIT
Project-URL: Homepage, https://smsaero.ru/
Project-URL: Repository, https://github.com/smsaero/smsaero_python_kannel/
Project-URL: Bug Tracker, https://github.com/smsaero/smsaero_python_kannel/issues
Project-URL: Help Center, https://smsaero.ru/support/
Keywords: smsaero,kannel,sms
Platform: any
Classifier: Development Status :: 5 - Production/Stable
Classifier: Environment :: Web Environment
Classifier: Environment :: Console
Classifier: Intended Audience :: Developers
Classifier: Intended Audience :: System Administrators
Classifier: Operating System :: OS Independent
Classifier: Programming Language :: Python
Classifier: Programming Language :: Python :: 3
Classifier: Programming Language :: Python :: 3 :: Only
Classifier: Programming Language :: Python :: 3.9
Classifier: Programming Language :: Python :: 3.10
Classifier: Programming Language :: Python :: 3.11
Classifier: Programming Language :: Python :: 3.12
Classifier: Programming Language :: Python :: 3.13
Classifier: Programming Language :: Python :: 3.14
Classifier: Programming Language :: Python :: Implementation :: CPython
Classifier: Topic :: Software Development :: Libraries :: Python Modules
Classifier: Topic :: Communications :: Telephony
Classifier: Topic :: Internet :: WWW/HTTP
Classifier: Topic :: Software Development :: Libraries :: Python Modules
Requires-Python: >=3.6
License-File: LICENSE
License-File: AUTHORS.md
Requires-Dist: setuptools
Requires-Dist: aiohttp>=3.9.1
Requires-Dist: requests>=2.31.0
Requires-Dist: phonenumbers>=8.13.40
Requires-Dist: python-dotenv>=1.0.0
Provides-Extra: dev
Requires-Dist: pytest>=8.2.2; extra == "dev"
Requires-Dist: flake8>=7.1.0; extra == "dev"
Requires-Dist: ruff>=0.4.10; extra == "dev"
Requires-Dist: pylint>=3.2.4; extra == "dev"
Requires-Dist: tox>=4.15.1; extra == "dev"
Requires-Dist: coverage>=7.5.4; extra == "dev"
Requires-Dist: bandit>=1.7.9; extra == "dev"
Requires-Dist: build>=1.2.1; extra == "dev"
Requires-Dist: twine>=5.1.1; extra == "dev"
Dynamic: author
Dynamic: author-email
Dynamic: classifier
Dynamic: description
Dynamic: description-content-type
Dynamic: download-url
Dynamic: home-page
Dynamic: keywords
Dynamic: license
Dynamic: license-file
Dynamic: maintainer
Dynamic: maintainer-email
Dynamic: platform
Dynamic: project-url
Dynamic: provides-extra
Dynamic: requires-dist
Dynamic: requires-python
Dynamic: summary
